<?xml version="1.0" encoding="UTF-8"?>
<!--
/**
 * Copyright (c) Codice Foundation
 *
 * This is free software: you can redistribute it and/or modify it under the terms of the GNU Lesser General Public License as published by the Free Software Foundation, either
 * version 3 of the License, or any later version.
 *
 * This program is distributed in the hope that it will be useful, but WITHOUT ANY WARRANTY; without even the implied warranty of MERCHANTABILITY or FITNESS FOR A PARTICULAR PURPOSE.
 * See the GNU Lesser General Public License for more details. A copy of the GNU Lesser General Public License is distributed along with this program and can be found at
 * <http://www.gnu.org/licenses/lgpl.html>.
 *
 **/
-->
<!--
=============================================================
Provides.xml
Services (OSGi) that catalog-ui-search PROVIDES to DDF
=============================================================
-->
<blueprint xmlns="http://www.osgi.org/xmlns/blueprint/v1.0.0">

    <!--
    =============================================================
    COMMON (used by two or more dependents)
    =============================================================
    -->

    <!-- Needed by both metacard app and query metacard app for now -->
    <service interface="ddf.catalog.data.MetacardType">
        <bean class="org.codice.ddf.catalog.ui.metacard.query.data.metacard.QueryMetacardTypeImpl"/>
    </service>

    <!-- Exposing endpoint util as a service to allow for system templates to be managed through
    the means of a Karaf command (reference injection) -->
    <service ref="endpointUtil" interface="org.codice.ddf.catalog.ui.api.EndpointUtility"/>

    <!--
    =============================================================
    SIMPLE APPS
    (AUTH/BUILD/CATALOG/PLATFORM/FEEDBACK/GEOCODER/LOGOUT/SESSION/USER)
    =============================================================
    -->

    <!--
    =============================================================
    DESCRIPTORS APPLICATION
    =============================================================
    -->

    <!--
    =============================================================
    LIST APPLICATION
    =============================================================
    -->

    <service interface="ddf.catalog.data.MetacardType">
        <bean class="org.codice.ddf.catalog.ui.metacard.workspace.ListMetacardTypeImpl"/>
    </service>

    <!-- This should have a service ranking lower than all other splitters. -->
    <service interface="org.codice.ddf.catalog.ui.splitter.Splitter" ranking="-100">
        <service-properties>
            <entry key="id" value="identity-splitter"/>
        </service-properties>
        <bean class="org.codice.ddf.catalog.ui.metacard.impl.IdentitySplitter"/>
    </service>

    <!--
    =============================================================
    METACARD APPLICATION
    =============================================================
    -->

    <bean id="workspaceMetacardType"
          class="org.codice.ddf.catalog.ui.metacard.workspace.WorkspaceMetacardType"/>
    <service ref="workspaceMetacardType" interface="ddf.catalog.data.MetacardType">
        <service-properties>
            <entry key="name" value="workspace"/>
            <!-- If the following entry changes, also change the metacard tag in WorkspaceMetacardType -->
            <entry key="access-controlled-tag" value="workspace"/>
        </service-properties>
    </service>

    <bean id="noteMetacardType" class="org.codice.ddf.catalog.ui.metacard.notes.NoteMetacardType"/>
    <service ref="noteMetacardType" interface="ddf.catalog.data.MetacardType">
        <service-properties>
            <entry key="name" value="ddf.metacard.NoteMetacardType"/>
            <entry key="id" value="resource-note"/>
        </service-properties>
    </service>

    <service ref="workspaceTransformer"
             interface="org.codice.ddf.catalog.ui.metacard.workspace.transformer.WorkspaceTransformer"/>

    <service ref="workspacePersistentStore"
             interface="org.codice.ddf.catalog.ui.subscription.SubscriptionsPersistentStore">
        <service-properties>
            <entry key="id"
                   value="org.codice.ddf.catalog.ui.query.monitor.impl.SubscriptionsPersistentStoreImpl"/>
        </service-properties>
    </service>

    <!-- Workspace Transforms -->

    <service
            interface="org.codice.ddf.catalog.ui.metacard.workspace.transformer.WorkspaceTransformation">
        <bean class="org.codice.ddf.catalog.ui.metacard.workspace.transformer.impl.QueryIdsParser"/>
    </service>

    <service
            interface="org.codice.ddf.catalog.ui.metacard.workspace.transformer.WorkspaceTransformation">
        <bean class="org.codice.ddf.catalog.ui.metacard.workspace.transformer.impl.QuerySortsParser"/>
    </service>

    <service
            interface="org.codice.ddf.catalog.ui.metacard.workspace.transformer.WorkspaceTransformation">
        <bean class="org.codice.ddf.catalog.ui.metacard.workspace.transformer.impl.WorkspaceMetacardsKeyToAssociations"/>
    </service>

    <service
            interface="org.codice.ddf.catalog.ui.metacard.workspace.transformer.WorkspaceTransformation">
        <bean class="org.codice.ddf.catalog.ui.metacard.workspace.transformer.impl.SrcToQuerySources"/>
    </service>

    <service
            interface="org.codice.ddf.catalog.ui.metacard.workspace.transformer.WorkspaceTransformation">
        <bean class="org.codice.ddf.catalog.ui.metacard.workspace.transformer.impl.RemoveMetacardTags"/>
    </service>

    <service
            interface="org.codice.ddf.catalog.ui.metacard.workspace.transformer.WorkspaceTransformation">
        <bean class="org.codice.ddf.catalog.ui.metacard.workspace.transformer.impl.EmbeddedListMetacardsHandler">
            <argument ref="metacardActionRegistry"/>
        </bean>
    </service>

    <service
            interface="org.codice.ddf.catalog.ui.metacard.workspace.transformer.WorkspaceTransformation">
        <bean class="org.codice.ddf.catalog.ui.metacard.workspace.transformer.impl.FilterBlankAccessIndividuals"/>
    </service>

    <!--
    =============================================================
    QUERY APPLICATION
    =============================================================
    -->

    <service ref="featureService"
             interface="org.codice.ddf.catalog.ui.query.geofeature.FeatureService"/>

    <!--
    =============================================================
    QUERY METACARD APPLICATION
    =============================================================
    -->

    <!--
    =============================================================
    SEARCH FORMS APPLICATION
    =============================================================
    -->

    <bean id="queryTemplateMetacardType"
          class="org.codice.ddf.catalog.ui.forms.data.QueryTemplateType"/>

    <bean id="attributeGroupMetacardType"
          class="org.codice.ddf.catalog.ui.forms.data.AttributeGroupType"/>

    <service ref="queryTemplateMetacardType" interface="ddf.catalog.data.MetacardType">
        <service-properties>
            <entry key="name" value="query-template"/>
            <!-- If the following entry changes, also change the metacard tag in QueryTemplateType -->
            <entry key="access-controlled-tag" value="query-template"/>
        </service-properties>
    </service>

    <service ref="attributeGroupMetacardType" interface="ddf.catalog.data.MetacardType">
        <service-properties>
            <entry key="name" value="attribute-group"/>
            <!-- If the following entry changes, also change the metacard tag in AttributeGroupType -->
            <entry key="access-controlled-tag" value="attribute-group"/>
        </service-properties>
    </service>

    <service interface="ddf.catalog.plugin.AccessPlugin">
        <bean class="org.codice.ddf.catalog.ui.forms.security.SystemTemplateAccessPlugin"/>
    </service>

    <service interface="ddf.catalog.plugin.PolicyPlugin">
        <bean class="org.codice.ddf.catalog.ui.forms.security.SystemTemplatePolicyPlugin">
            <argument ref="accessControlSecurityConfiguration"/>
        </bean>
    </service>

    <!--
    =============================================================
    ASYNC/LISTENERS/NOTIFICATIONS
    =============================================================
    -->

    <service ref="workspaceQueryService"
             interface="org.codice.ddf.catalog.ui.query.monitor.api.WorkspaceQueryService"/>

    <!--
    =============================================================
    SHARING POLICY
    =============================================================
    -->

    <service interface="ddf.catalog.plugin.PreQueryPlugin">
        <bean class="org.codice.ddf.catalog.ui.security.accesscontrol.AccessControlPreQueryPlugin">
            <argument ref="filterBuilder"/>
            <argument ref="subjectIdentity"/>
            <argument ref="accessControlTags"/>
            <argument ref="accessControlSecurityConfiguration"/>
        </bean>
    </service>

    <service interface="ddf.catalog.plugin.AccessPlugin">
        <bean class="org.codice.ddf.catalog.ui.security.accesscontrol.AccessControlAccessPlugin">
            <argument ref="subjectIdentity"/>
        </bean>
    </service>

    <service interface="ddf.security.policy.extension.PolicyExtension">
        <bean class="org.codice.ddf.catalog.ui.security.accesscontrol.AccessControlPolicyExtension">
            <argument ref="accessControlSecurityConfiguration"/>
            <argument ref="subjectIdentity"/>
        </bean>
    </service>

    <service interface="ddf.catalog.plugin.PolicyPlugin">
        <bean class="org.codice.ddf.catalog.ui.security.accesscontrol.AccessControlPolicyPlugin"/>
    </service>

    <service interface="ddf.catalog.plugin.PreIngestPlugin">
        <bean class="org.codice.ddf.catalog.ui.security.accesscontrol.AccessControlPreIngestPlugin">
            <argument ref="subjectIdentity"/>
        </bean>
    </service>

</blueprint>